nara_wpe/__init__.py
nara_wpe/benchmark_online_wpe.py
nara_wpe/ntt_wpe.py
nara_wpe/test_utils.py
nara_wpe/tf_wpe.py
nara_wpe/torch_wpe.py
nara_wpe/utils.py
nara_wpe/wpe.py
nara_wpe-0.0.11.dist-info/LICENSE
nara_wpe-0.0.11.dist-info/METADATA
nara_wpe-0.0.11.dist-info/WHEEL
nara_wpe-0.0.11.dist-info/top_level.txt
nara_wpe-0.0.11.dist-info/RECORD
