Metadata-Version: 2.1
Name: nara_wpe
Version: 0.0.11
Summary: Weighted Prediction Error for speech dereverberation
Home-page: https://github.com/fgnt/nara_wpe
Author: Department of Communications Engineering, Paderborn University
Author-email: sek@nt.upb.de
License: MIT
Keywords: speech
Classifier: Development Status :: 3 - Alpha
Classifier: Intended Audience :: Developers
Classifier: Topic :: Software Development :: Build Tools
Classifier: License :: OSI Approved :: MIT License
Classifier: Programming Language :: Python :: 3.7
Classifier: Programming Language :: Python :: 3.8
Classifier: Programming Language :: Python :: 3.9
Classifier: Programming Language :: Python :: 3.10
Classifier: Programming Language :: Python :: 3.11
Classifier: Programming Language :: Python :: 3.12
License-File: LICENSE
Requires-Dist: pathlib2; python_version < "3.0"
Requires-Dist: numpy
Requires-Dist: tqdm
Requires-Dist: soundfile
Requires-Dist: bottleneck
Requires-Dist: click
Provides-Extra: dev
Requires-Dist: check-manifest; extra == "dev"
Provides-Extra: test
Requires-Dist: pytest; extra == "test"
Requires-Dist: coverage; extra == "test"
Requires-Dist: jupyter; extra == "test"
Requires-Dist: matplotlib; extra == "test"
Requires-Dist: scipy; extra == "test"
Requires-Dist: tensorflow==1.12.0; python_version < "3.7" and extra == "test"
Requires-Dist: pytest-cov; extra == "test"
Requires-Dist: codecov; extra == "test"
Requires-Dist: pandas; extra == "test"
Requires-Dist: torch; extra == "test"
Requires-Dist: cached_property; extra == "test"
Requires-Dist: zmq; extra == "test"
Requires-Dist: pyzmq; extra == "test"
Requires-Dist: pymatbridge; extra == "test"
